Metadata-Version: 1.0
Name: aelbatal-distributions
Version: 0.1
Summary: Gaussian and binomial distributions, by Adham El-Batal for Udacity ML Engineer course.
Home-page: UNKNOWN
Author: UNKNOWN
Author-email: UNKNOWN
License: UNKNOWN
Platform: UNKNOWN
